fastapi_easyauth/__init__.py
fastapi_easyauth/easyauth.py
fastapi_easyauth/exp.py
fastapi_easyauth/jwt.py
fastapi_easyauth/sessionauth.py
fastapi_easyauth/models/__init__.py
fastapi_easyauth/models/base.py
fastapi_easyauth/models/usermodels.py
fastapi_easyauth/schemas/__init__.py
fastapi_easyauth/schemas/user_schemas.py
fastapi_easyauth-0.3.3.dist-info/METADATA
fastapi_easyauth-0.3.3.dist-info/WHEEL
fastapi_easyauth-0.3.3.dist-info/top_level.txt
fastapi_easyauth-0.3.3.dist-info/RECORD
