Metadata-Version: 2.1
Name: fastapi-easyauth
Version: 0.3.3
Summary: A library for quickly creating authentication using JWT and Cookies. Or storing a JWT token in a session
Home-page: https://github.com/GwenB1ade/fastapi-easyauth
Author: duckduck
Author-email: dimondtp@gmail.com
Project-URL: GitHub, https://github.com/GwenB1ade/fastapi-easyauth
Keywords: fastapi fastapi-jwt fastapi-easyauth fastapi-auth sessioauth SessioAuth
Classifier: Programming Language :: Python :: 3.11
Classifier: License :: OSI Approved :: MIT License
Classifier: Operating System :: OS Independent
Requires-Python: >=3.9
Requires-Dist: fastapi
Requires-Dist: fastapi-jwt
Requires-Dist: pydantic
Requires-Dist: itsdangerous
Requires-Dist: sqlalchemy
